{
  "dotaId": "diffusal_blade",
  "attrib": "+ <font color=\"#ffffff\"><b>20</b></font>/35 к ловкости<br/>+ 6/10 к интеллекту",
  "cd": 8.0,
  "components": [
    "blade_of_alacrity",
    "blade_of_alacrity",
    "robe"
  ],
  "qual": "artifact",
  "notes": "Мгновенно уничтожает призванных существ.Замедление длится 4 секунды.",
  "desc": "Активируемая: Purge — снимает с выбранного юнита все бонусы, замедляет его, а также наносит урон, если цель является призванным юнитом.\r<br/>Пассивная: Feedback — ваши атаки сжигают  25 маны врага и наносят ему такое же количество урона. Можно улучшить.<br/><br/>Эффекты от нескольких Feedback или схожих способностей не складываются.",
  "dname": "Diffusal Blade lvl1",
  "mc": false,
  "img": "diffusal_blade_lg.png",
  "lore": "Заговоренный меч, рассекающий души врагов.",
  "id": 174,
  "created": true,
  "cost": 3150
}