{
  "dotaId": "silver_edge",
  "id": 249,
  "img": "silver_edge_lg.png",
  "dname": "Silver Edge",
  "qual": "epic",
  "cost": 5450,
  "desc": "Активируемая: Shadow Walk — делает вас невидимым на время действия или до момента вашей атаки или использования заклинания. Пока Shadow Walk активна, вы движетесь на 20% быстрее и можете проходить сквозь юнитов. Атака, раскрывающая невидимость, нанесет 225 дополнительного урона, отключит пассивные способности цели и уменьшит весь наносимый ею урон.<br \/>\r\nПассивная: Lesser Maim — каждая атака получает шанс уменьшить скорость передвижения врага на 4.0 сек.",
  "notes": "Удар, раскрывающий невидимость, никогда не промахивается.",
  "attrib": "+ 32 УРОНА<br/>+ 30 к скорости атаки<br/>+ 16 к силе<br/>ШАНС ИСКАЛЕЧИТЬ: 15%<br/>ЗАМЕДЛЕНИЕ ПЕРЕДВИЖЕНИЯ ОТ ТРАВМЫ: 20%<br/>ЗАМЕДЛЕНИЕ АТАКИ ОТ ТРАВМЫ: 20<br/>ДЛИТЕЛЬНОСТЬ ТРАВМЫ: 4<br/>ДЛИТЕЛЬНОСТЬ НЕВИДИМОСТИ: 14<br/>УРОН ИЗ НЕВИДИМОСТИ: 225<br/>СНИЖЕНИЕ УРОНА ЦЕЛИ: 40%<br/>ДЛИТЕЛЬНОСТЬ УМЕНЬШЕНИЯ УРОНА: 5",
  "mc": 75,
  "cd": 24,
  "lore": "Повергнув несправедливого правителя, этот клинок лишь развязал гражданскую войну.",
  "components": [
    "invis_sword",
    "sange"
  ],
  "created": true
}