{"AbilityBuild":{"AbilityOrder":{"1":"faceless_void_time_walk","2":"faceless_void_backtrack","3":"faceless_void_time_lock","4":"faceless_void_time_walk","5":"faceless_void_backtrack","6":"faceless_void_chronosphere","7":"faceless_void_time_walk","8":"faceless_void_backtrack","9":"faceless_void_time_lock","10":"faceless_void_time_walk","11":"faceless_void_chronosphere","12":"faceless_void_backtrack","13":"faceless_void_time_lock","14":"faceless_void_time_lock","15":"attribute_bonus","16":"faceless_void_chronosphere","17":"attribute_bonus","18":"attribute_bonus","19":"attribute_bonus","20":"attribute_bonus","21":"attribute_bonus","22":"attribute_bonus","23":"attribute_bonus","24":"attribute_bonus","25":"attribute_bonus"},"AbilityTooltips":{"faceless_void_chronosphere":"Купол, в котором можем ходить только мы, т.е. можно убивать.","faceless_void_time_walk":"Наш Escape.","faceless_void_time_lock":"Наш стан.","faceless_void_backtrack":"Увороты, которые не контрятся МКБ и дуэлью Легионки."}},"Hero":"faceless_void","ItemBuild":{"ItemTooltips":{"greater_crit":"Криты.","ultimate_scepter":"Неплохо улучшает нашу ульту.","mjollnir":"Скорость атаки + урон.","power_treads":"Скорость атаки (ставим на ловкость).","mask_of_madness":"Быстрее убьем в куполе. Покупаем первым итемом.","bfury":"Урон + важный итем для фарма."},"Items":{"Начальные предметы":["tango","quelling_blade","stout_shield"],"Early Game":["mask_of_madness","power_treads"],"Mid Game":["bfury","greater_crit"],"Late Game":["ultimate_scepter","mjollnir"],"Финальный билд MB44R":["mask_of_madness","power_treads","bfury","greater_crit","ultimate_scepter","mjollnir"]}},"Title":"Gish.Faceless Void "}