[
    {
        "dname": "Crypt Swarm",
        "affects": "Способность: <b><font color=\"#ffffff\">направленная на юнита, направленная на точку</font></b><br/>Действует на <b><font color=\"#ffffff\">вражеских существ</font></b><br/>ТИП УРОНА: <b><font color=\"#ffffff\">магический</font></b><br/>СКВОЗЬ ИММУНИТЕТ К МАГИИ: <b><font color=\"#ffffff\">Нет</font></b>",
        "desc": "Кробелус посылает вперед стаю крылатых тварей, наносящих урон врагам на своем пути.",
        "notes": "Наносит урон юнитам на расстоянии до 1100 единиц.",
        "dmg": "УРОНА: <b><font color=\"#ffffff\">75/150/225/300</font></b>",
        "attrib": "ДАЛЬНОСТЬ ПРИМЕНЕНИЯ: <b><font color=\"#ffffff\">810/810/810/810</font></b>",
        "cmb": "<img alt=\"Расход маны\" title=\"Расход маны\" class=\"manaImg\" src=\"http://cdn.dota2.com/apps/dota2/images/tooltips/mana.png\" width=\"16\" height=\"16\" border=\"0\"/> 105/120/140/165<br/><img alt=\"Перезарядка\" title=\"Перезарядка\" class=\"cooldownImg\" src=\"http://cdn.dota2.com/apps/dota2/images/tooltips/cooldown.png\" width=\"16\" height=\"16\" border=\"0\"/> 8",
        "lore": "Во время своих путешествий в загробный мир Кробелус забирает с собой души проклятых, материализуя их стаей летучих мышей в нашем мире.",
        "hurl": "Death_Prophet",
        "name": "death_prophet_carrion_swarm",
        "youtube":"z_uGWWazyqg",
        "id": 0
    },
    {
        "dname": "Silence",
        "affects": "Способность: <b><font color=\"#ffffff\">направленная на точку</font></b><br/>СКВОЗЬ ИММУНИТЕТ К МАГИИ: <b><font color=\"#ffffff\">Нет</font></b>",
        "desc": "Не дает использовать заклинания врагам в указанной области.",
        "notes": "Не запрещает использовать предметы.",
        "dmg": "",
        "attrib": "РАДИУС: <b><font color=\"#ffffff\">425</font></b><br/>ДЛИТЕЛЬНОСТЬ: <b><font color=\"#ffffff\">3/4/5/6</font></b>",
        "cmb": "<img alt=\"Расход маны\" title=\"Расход маны\" class=\"manaImg\" src=\"http://cdn.dota2.com/apps/dota2/images/tooltips/mana.png\" width=\"16\" height=\"16\" border=\"0\"/> 80/80/80/80<br/><img alt=\"Перезарядка\" title=\"Перезарядка\" class=\"cooldownImg\" src=\"http://cdn.dota2.com/apps/dota2/images/tooltips/cooldown.png\" width=\"16\" height=\"16\" border=\"0\"/> 15",
        "lore": "Кробелус видит лишь безмолвное будущее, вглядываясь в смертное предначертание своего врага.",
        "hurl": "Death_Prophet",
        "name": "death_prophet_silence",
        "youtube":"eLBBXHVFYgU",
        "id": 1
    },
    {
        "dname": "Witchcraft",
        "affects": "Способность: <b><font color=\"#ffffff\">пассивная</font></b>",
        "desc": "Увеличивает мощь заклинаний Death Prophet и дает дополнительную скорость передвижения. Уменьшет расход маны и время перезарядки Crypt Swarm и Silence, а заклинание Exorcism призывает большее количество духов.",
        "notes": "",
        "dmg": "",
        "attrib": "СКОРОСТЬ ПЕРЕДВИЖЕНИЯ: <b><font color=\"#ffffff\">5%/10%/15%/20%</font></b><br/>УМЕНЬШЕНИЕ РАСХОДА МАНЫ: <b><font color=\"#ffffff\">10/15/20/25</font></b><br/>УМЕНЬШЕНИЕ ПЕРЕЗАРЯДКИ: <b><font color=\"#ffffff\">1/2/3/4</font></b><br/>ДОПОЛНИТЕЛЬНЫЕ ДУХИ: <b><font color=\"#ffffff\">3/4/5/6</font></b>",
        "cmb": "",
        "lore": "Новые души пополняют репертуар Кробелус, усиливая её колдовскую мощь.",
        "hurl": "Death_Prophet",
        "name": "death_prophet_witchcraft",
        "id": 2
    },
    {
        "dname": "Exorcism",
        "affects": "Способность: <b><font color=\"#ffffff\">ненаправленная</font></b><br/>ТИП УРОНА: <b><font color=\"#71a9ea\">физический</font></b><br/>СКВОЗЬ ИММУНИТЕТ К МАГИИ: <b><font color=\"#70EA72\">Да</font></b>",
        "desc": "Кробелус выпускает злобных духов, высасывающих жизнь из вражеских юнитов и сооружений поблизости. Через 30 секунд они возвращаются к хозяйке, исцеляя ее. Сила исцеления зависит от количества нанесенного духами урона.",
        "notes": "Радиус указывает область вокруг вас, в которой духи будут атаковать.<br/>Урон от духов не уменьшается способностями, блокирующими урон.",
        "dmg": "",
        "attrib": "РАДИУС: <b><font color=\"#ffffff\">700/700/700</font></b><br/>ДУХОВ: <b><font color=\"#ffffff\">6/13/21</font></b><br/>ЗДОРОВЬЯ ВОССТ.: <b><font color=\"#ffffff\">25%/25%/25%</font></b><br/>УРОН ДУХОВ: <b><font color=\"#ffffff\">55/55/55</font></b>",
        "cmb": "<img alt=\"Расход маны\" title=\"Расход маны\" class=\"manaImg\" src=\"http://cdn.dota2.com/apps/dota2/images/tooltips/mana.png\" width=\"16\" height=\"16\" border=\"0\"/> 200/300/400<br/><img alt=\"Перезарядка\" title=\"Перезарядка\" class=\"cooldownImg\" src=\"http://cdn.dota2.com/apps/dota2/images/tooltips/cooldown.png\" width=\"16\" height=\"16\" border=\"0\"/> 145",
        "lore": "Осколки прошлых жизней баньши на время материализуются, чтобы сеять ужас в настоящем.",
        "hurl": "Death_Prophet",
        "name": "death_prophet_exorcism",
        "youtube":"UpxNoiCXx1g",
        "id": 3
    }
]