{
	"Hero":"enchantress",
	"Title":"Enchantres Jungle Repick build",
	"GuideRevision":"1",
	"FileVersion":"1",

	"ItemBuild":
	{
		"Items":
		{
			"startingItems":
			[
				"gloves"
			],
			"earlyGame":
			[
				"hand_of_midas",
				"power_treads"
			],
			"coreItems":
			[
				"bloodstone",
				"ultimate_scepter"
			],
			"luxury":
			[
				"sphere",
				"travel_boots",
				"assault",
				"veil_of_discord",
				"black_king_bar",
				"invis_sword",
				"shivas_guard"
			]
		}
	},

	"AbilityBuild":
	{
		"AbilityOrder":
		{
			"1":"enchantress_enchant",
			"2":"enchantress_untouchable",
			"3":"enchantress_enchant",
			"4":"enchantress_untouchable",
			"5":"enchantress_enchant",
			"6":"enchantress_impetus",
			"7":"enchantress_enchant",
			"8":"enchantress_untouchable",
			"9":"enchantress_untouchable",
			"10":"enchantress_natures_attendants",
			"11":"enchantress_impetus",
			"12":"enchantress_natures_attendants",
			"13":"enchantress_natures_attendants",
			"14":"enchantress_natures_attendants",
			"15":"attribute_bonus",
			"16":"enchantress_impetus",
			"17":"attribute_bonus",
			"18":"attribute_bonus",
			"19":"attribute_bonus",
			"20":"attribute_bonus",
			"21":"attribute_bonus",
			"22":"attribute_bonus",
			"23":"attribute_bonus",
			"24":"attribute_bonus",
			"25":"attribute_bonus"
		}
	}
}
