{
	"Hero":"troll_warlord",
	"Title":"Troll Wralord (TPSF)",
	"GuideRevision":"1",
	"FileVersion":"1",

	"ItemBuild":
	{
		"Items":
		{
			"startingItems":
			[
				"branches",
				"branches",
				"flask",
				"ring_of_protection",
				"tango",
				"clarity"
			],
			"earlyGame":
			[
				"boots",
				"stout_shield",
				"poor_mans_shield"
			],
			"coreItems":
			[
				"phase_boots",
				"helm_of_the_dominator",
				"blink",
				"invis_sword",
				"vanguard"
			],
			"luxury":
			[
				"bloodstone",
				"manta",
				"monkey_king_bar",
				"ethereal_blade",
				"satanic",
				"abyssal_blade",
				"greater_crit",
				"butterfly",
				"assault",
				"heart",
				"sange_and_yasha",
				"travel_boots"
			],
			"Final iten":
			[
				"rapier"
			]
		}
	},

	"AbilityBuild":
	{
		"AbilityOrder":
		{
			"1":"troll_warlord_berserkers_rage",
			"2":"troll_warlord_whirling_axes_ranged",
			"3":"troll_warlord_whirling_axes_ranged",
			"4":"troll_warlord_fervor",
			"5":"troll_warlord_whirling_axes_ranged",
			"6":"troll_warlord_battle_trance",
			"7":"troll_warlord_whirling_axes_ranged",
			"8":"troll_warlord_fervor",
			"9":"troll_warlord_fervor",
			"10":"troll_warlord_fervor",
			"11":"troll_warlord_battle_trance",
			"12":"troll_warlord_berserkers_rage",
			"13":"troll_warlord_berserkers_rage",
			"14":"troll_warlord_berserkers_rage",
			"15":"attribute_bonus",
			"16":"troll_warlord_battle_trance",
			"17":"attribute_bonus",
			"18":"attribute_bonus",
			"19":"attribute_bonus",
			"20":"attribute_bonus",
			"21":"attribute_bonus",
			"22":"attribute_bonus",
			"23":"attribute_bonus",
			"24":"attribute_bonus",
			"25":"attribute_bonus"
		}
	}
}
